LICENSE.txt
MANIFEST.in
README.rst
setup.py
angrytest/__init__.py
angrytest/pypitestangry.py
angrytest.egg-info/PKG-INFO
angrytest.egg-info/SOURCES.txt
angrytest.egg-info/dependency_links.txt
angrytest.egg-info/top_level.txt