Metadata-Version: 1.1
Name: angrytest
Version: 1.3.0
Summary: Test upload to pypi
Home-page: https://github.com/famishedrover/testUploadPypi
Author: Angryziber
Author-email: mudit.verma2014@gmail.com
License: MIT
Keywords: test upload script
Platform: UNKNOWN
Classifier: Development Status :: 3 - Alpha
Classifier: Intended Audience :: Developers
Classifier: Topic :: Software Development :: Build Tools
Classifier: License :: OSI Approved :: MIT License
Classifier: Programming Language :: Python :: 2
Classifier: Programming Language :: Python :: 2.7
